pedal/__init__.py
pedal/__main__.py
pedal/quick.py
pedal/assertions/__init__.py
pedal/assertions/assertions.py
pedal/assertions/classes.py
pedal/assertions/commands.py
pedal/assertions/constants.py
pedal/assertions/feedbacks.py
pedal/assertions/functions.py
pedal/assertions/organizers.py
pedal/assertions/positive.py
pedal/assertions/runtime.py
pedal/assertions/setup.py
pedal/assertions/static.py
pedal/assertions/testing_libraries.py
pedal/assertions/unittest.py
pedal/cait/__init__.py
pedal/cait/ast_dump_magic.py
pedal/cait/ast_helpers.py
pedal/cait/ast_map.py
pedal/cait/cait_api.py
pedal/cait/cait_node.py
pedal/cait/constants.py
pedal/cait/ct_map.py
pedal/cait/easy_node.py
pedal/cait/find_node.py
pedal/cait/node_refactory.py
pedal/cait/stretchy_tree_matching.py
pedal/command_line/__init__.py
pedal/command_line/command_line.py
pedal/command_line/mocks.py
pedal/command_line/modes.py
pedal/command_line/pipeline.py
pedal/command_line/report.py
pedal/command_line/verify.py
pedal/core/__init__.py
pedal/core/commands.py
pedal/core/config_bundle.py
pedal/core/config_job.py
pedal/core/environment.py
pedal/core/errors.py
pedal/core/feedback.py
pedal/core/feedback_category.py
pedal/core/final_feedback.py
pedal/core/formatting.py
pedal/core/location.py
pedal/core/report.py
pedal/core/resolver.py
pedal/core/scoring.py
pedal/core/submission.py
pedal/core/tag.py
pedal/core/tool.py
pedal/environments/__init__.py
pedal/environments/blockpy.py
pedal/environments/gradescope.py
pedal/environments/jupyter.py
pedal/environments/nbgrader.py
pedal/environments/none.py
pedal/environments/quick.py
pedal/environments/sandbox.py
pedal/environments/standard.py
pedal/environments/terminal.py
pedal/environments/vpl.py
pedal/extensions/__init__.py
pedal/extensions/drafter.py
pedal/extensions/microbit.py
pedal/extensions/plotting.py
pedal/extensions/turtles.py
pedal/mistakes/__init__.py
pedal/mistakes/ins_test_8_5.py
pedal/mistakes/instructor_append.py
pedal/mistakes/instructor_files.py
pedal-2.9.2.dist-info/LICENSE
pedal-2.9.2.dist-info/METADATA
pedal-2.9.2.dist-info/WHEEL
pedal-2.9.2.dist-info/entry_points.txt
pedal-2.9.2.dist-info/top_level.txt
pedal-2.9.2.dist-info/RECORD
