Metadata-Version: 2.1
Name: pedal
Version: 2.9.2
Summary: Tools to provide feedback on student code.
Home-page: https://pedal-edu.github.io/pedal
Author: acbart,lukesg08
Author-email: acbart@udel.edu
License: Creative Commons Attribution-Noncommercial-Share Alike license
Keywords: feedback education teaching program analysis tifa cait sandbox pedal grading grader grade
Classifier: Programming Language :: Python :: 3
Classifier: Intended Audience :: Education
Classifier: Topic :: Education
Requires-Python: >=3.8
License-File: LICENSE
Requires-Dist: tabulate
